cplan/__init__.py
cplan/createPlan.py
cplan/errors.py
cplan-0.0.3.dist-info/LICENSE
cplan-0.0.3.dist-info/METADATA
cplan-0.0.3.dist-info/WHEEL
cplan-0.0.3.dist-info/top_level.txt
cplan-0.0.3.dist-info/RECORD
