Metadata-Version: 2.1
Name: cplan
Version: 0.0.3
Summary: This is a package for creating plans.
Home-page: https://github.com/seoul2k/cPlan
Author: xiongtianshuo
Author-email: Mr_Xiongts@163.com
License: UNKNOWN
Project-URL: Bug Tracker, https://github.com/seoul2k/cPlan/issues
Platform: UNKNOWN
Classifier: Development Status :: 4 - Beta
Classifier: Operating System :: OS Independent
Classifier: Intended Audience :: Developers
Classifier: License :: OSI Approved :: BSD License
Classifier: Programming Language :: Python
Classifier: Programming Language :: Python :: Implementation
Classifier: Programming Language :: Python :: 2
Classifier: Programming Language :: Python :: 2.7
Classifier: Programming Language :: Python :: 3
Classifier: Programming Language :: Python :: 3.4
Classifier: Programming Language :: Python :: 3.5
Classifier: Programming Language :: Python :: 3.6
Classifier: Programming Language :: Python :: 3.8
Classifier: Topic :: Software Development :: Libraries
Requires-Python: >=3.6
License-File: LICENSE
Requires-Dist: xlwt
